celltometry/__init__.py
celltometry/dists.py
celltometry/metrics.py
celltometry/workflows.py
celltometry-0.0.1.dist-info/LICENSE
celltometry-0.0.1.dist-info/METADATA
celltometry-0.0.1.dist-info/WHEEL
celltometry-0.0.1.dist-info/top_level.txt
celltometry-0.0.1.dist-info/RECORD
