Metadata-Version: 2.1
Name: celltometry
Version: 0.0.1
Summary: Learn single-cell data structure through topological bases, graphs and layouts
Home-page: https://github.com/davisidarta/celltometry
Author: Davi Sidarta-Oliveira
Author-email: davisidarta@fcm.unicamp.br
License: UNKNOWN
Project-URL: Bug Tracker, https://github.com/davisidarta/celltometry/issues
Platform: UNKNOWN
Classifier: Programming Language :: Python :: 3
Classifier: License :: OSI Approved :: MIT License
Classifier: Operating System :: OS Independent
Requires-Python: >=3.6
License-File: LICENSE
